colorarg/__init__.py
colorarg/color_arg.py
venv/test.py
colorarg-0.2.2.dist-info/METADATA
colorarg-0.2.2.dist-info/WHEEL
colorarg-0.2.2.dist-info/top_level.txt
colorarg-0.2.2.dist-info/RECORD
