Metadata-Version: 2.1
Name: colorarg
Version: 0.2.2
Summary: Beautiful, colorful argparser.
License: BSD-2-Clause license and the permission of authors
Requires-Python: >=3.8
Requires-Dist: colorama
